timber_nds/__init__.py
timber_nds/calculation.py
timber_nds/design.py
timber_nds/settings.py
timber_nds-0.1.2.dist-info/LICENSE
timber_nds-0.1.2.dist-info/METADATA
timber_nds-0.1.2.dist-info/WHEEL
timber_nds-0.1.2.dist-info/top_level.txt
timber_nds-0.1.2.dist-info/RECORD
