Metadata-Version: 2.2
Name: timber_nds
Version: 0.1.2
Summary: Package for timber design calculations based on NDS standards.
Author-email: Angel Navarro-Mora <ahnavarro@itcr.ac.cr>
License: MIT License
Project-URL: Homepage, https://github.com/ingahnavarro/timber_nds
Classifier: License :: OSI Approved :: MIT License
Classifier: Programming Language :: Python :: 3
Classifier: Programming Language :: Python :: 3.9
Classifier: Programming Language :: Python :: 3.10
License-File: LICENSE
